grscheller/untyped/__init__.py
grscheller/untyped/nada.py
grscheller_untyped-0.4.1.dist-info/LICENSE
grscheller_untyped-0.4.1.dist-info/WHEEL
grscheller_untyped-0.4.1.dist-info/METADATA
grscheller_untyped-0.4.1.dist-info/RECORD
