Metadata-Version: 2.1
Name: grscheller.untyped
Version: 0.4.1
Summary: ### Untyped Modules - OBSOLETED!
Author-email: "Geoffrey R. Scheller" <geoffrey@scheller.com>
Requires-Python: >=3.11
Classifier: Development Status :: 7 - Inactive
Classifier: Programming Language :: Python :: 3
Classifier: Operating System :: OS Independent
Classifier: License :: OSI Approved :: Apache Software License
Project-URL: Changelog, https://github.com/grscheller/untyped/blob/main/CHANGELOG.md
Project-URL: Documentation, https://github.com/grscheller/untyped/tree/main/docs/API
Project-URL: Source, https://github.com/grscheller/untyped
